enosimulator/__init__.py
enosimulator/__main__.py
enosimulator/_version.py
enosimulator/containers.py
enosimulator/main.py
enosimulator/types_.py
enosimulator/backend/__init__.py
enosimulator/backend/app.py
enosimulator/backend/schema.sql
enosimulator/config/config.json
enosimulator/config/secrets.json
enosimulator/config/examples/azure.config.json
enosimulator/config/examples/azure.secrets.json
enosimulator/config/examples/docker.config.json
enosimulator/config/examples/docker.secrets.json
enosimulator/config/examples/hetzner.config.json
enosimulator/config/examples/hetzner.secrets.json
enosimulator/infra/azure/config/.gitkeep
enosimulator/infra/azure/data/.gitkeep
enosimulator/infra/azure/logs/.gitkeep
enosimulator/infra/azure/templates/build.sh
enosimulator/infra/azure/templates/configure.sh
enosimulator/infra/azure/templates/main.tf
enosimulator/infra/azure/templates/outputs.tf
enosimulator/infra/azure/templates/variables.tf
enosimulator/infra/azure/templates/versions.tf
enosimulator/infra/azure/templates/data/checker.sh
enosimulator/infra/azure/templates/data/docker-compose.yml
enosimulator/infra/azure/templates/data/engine.sh
enosimulator/infra/azure/templates/data/vulnbox.sh
enosimulator/infra/hetzner/config/.gitkeep
enosimulator/infra/hetzner/data/.gitkeep
enosimulator/infra/hetzner/logs/.gitkeep
enosimulator/infra/hetzner/templates/build.sh
enosimulator/infra/hetzner/templates/configure.sh
enosimulator/infra/hetzner/templates/main.tf
enosimulator/infra/hetzner/templates/outputs.tf
enosimulator/infra/hetzner/templates/variables.tf
enosimulator/infra/hetzner/templates/versions.tf
enosimulator/infra/hetzner/templates/data/checker.sh
enosimulator/infra/hetzner/templates/data/docker-compose.yml
enosimulator/infra/hetzner/templates/data/engine.sh
enosimulator/infra/hetzner/templates/data/vulnbox.sh
enosimulator/infra/local/templates/main.tf
enosimulator/infra/local/templates/versions.tf
enosimulator/setup/__init__.py
enosimulator/setup/setup.py
enosimulator-0.3.4.dist-info/LICENSE
enosimulator-0.3.4.dist-info/METADATA
enosimulator-0.3.4.dist-info/WHEEL
enosimulator-0.3.4.dist-info/entry_points.txt
enosimulator-0.3.4.dist-info/top_level.txt
enosimulator-0.3.4.dist-info/RECORD
