Metadata-Version: 2.1
Name: enosimulator
Version: 0.3.4
Summary: Simulating an attack defense CTF competition using the game engine and services provided by Enowars
Home-page: https://github.com/ashiven/enosimulator
Author: Jannik Novak
Author-email: nevisha@pm.me
Classifier: Development Status :: 3 - Alpha
Classifier: License :: OSI Approved :: MIT License
Classifier: Programming Language :: Python :: 3.11
Requires-Python: >=3.11
License-File: LICENSE
Requires-Dist: aenum ==3.1.15
Requires-Dist: aiofiles ==23.2.1
Requires-Dist: beautifulsoup4 ==4.11.1
Requires-Dist: dependency-injector ==4.41.0
Requires-Dist: enochecker-core ==0.10.0
Requires-Dist: Flask ==2.3.1
Requires-Dist: Flask-RESTful ==0.3.10
Requires-Dist: httpx ==0.25.0
Requires-Dist: jsons ==1.6.3
Requires-Dist: matplotlib ==3.7.0
Requires-Dist: numpy ==1.24.2
Requires-Dist: paramiko ==3.3.1
Requires-Dist: python-dotenv ==1.0.0
Requires-Dist: Requests ==2.31.0
Requires-Dist: rich ==13.6.0
Requires-Dist: scipy ==1.11.3
Requires-Dist: selenium ==4.14.0
Requires-Dist: tenacity ==8.2.2
Requires-Dist: webdriver-manager ==4.0.1
